databricks_tool/__init__.py
databricks_tool/query_tool.py
databricks_tool-0.1.dist-info/METADATA
databricks_tool-0.1.dist-info/WHEEL
databricks_tool-0.1.dist-info/entry_points.txt
databricks_tool-0.1.dist-info/top_level.txt
databricks_tool-0.1.dist-info/RECORD
